[{"_uuid":"1","_title":"Mercurio","_description":"Mira, soy Mercurio, comprame","_imageURL":"https://media.gq.com.mx/photos/623f7ab8eaa378c48316e6db/3:2/w_2556,h_1704,c_limit/mercurio.jpg","_unit":"1","_stock":20,"_pricePerUnit":150,"_category":"Planeta"},{"_uuid":"2","_title":"Venus","_description":"Mira, soy Venus, comprame","_imageURL":"https://www.nationalgeographic.com.es/medio/2022/06/30/el-planeta-venus_d6349041_800x800.jpg","_unit":"1","_stock":10,"_pricePerUnit":120,"_category":"Planeta"},{"_uuid":"3","_title":"Tierra","_description":"Mira, soy Tierra, comprame","_imageURL":"https://www.nationalgeographic.com.es/medio/2022/06/30/el-planeta-tierra_608b9ad4_800x800.jpg","_unit":"1","_stock":20,"_pricePerUnit":350,"_category":"Planeta"},{"_uuid":"4","_title":"Marte","_description":"Mira, soy Marte, comprame","_imageURL":"https://www.nationalgeographic.com.es/medio/2022/06/30/el-planeta-marte_e9b53cea_800x758.jpg","_unit":"1","_stock":30,"_pricePerUnit":250,"_category":"Planeta"},{"_uuid":"5","_title":"Jupiter","_description":"Mira, soy Jupiter, comprame","_imageURL":"https://www.nationalgeographic.com.es/medio/2022/06/30/el-planeta-jupiter_62aed912_800x800.jpg","_unit":"1","_stock":60,"_pricePerUnit":150,"_category":"Planeton"},{"_uuid":"6","_title":"Saturno","_description":"Mira, soy Saturno, comprame","_imageURL":"https://www.ngenespanol.com/wp-content/uploads/2023/06/saturno-asi-es-el-planeta-menos-denso-del-sistema-solar.jpg","_unit":"1","_stock":40,"_pricePerUnit":200,"_category":"Planeton"},{"_uuid":"7","_title":"Urano","_description":"Mira, soy Urano, comprame","_imageURL":"https://www.nationalgeographic.com.es/medio/2022/06/30/el-planeta-urano_0c7434f8_800x800.jpg","_unit":"1","_stock":50,"_pricePerUnit":150,"_category":"Planeton"},{"_uuid":"8","_title":"Neptuno","_description":"Mira, soy Neptuno, comprame","_imageURL":"https://www.nationalgeographic.com.es/medio/2022/06/30/el-planeta-neptuno_3405d5aa_800x798.jpg","_unit":"1","_stock":30,"_pricePerUnit":130,"_category":"Planeta"}]